cli_badges/__init__.py
cli_badges/cli_badges.py
cli_badges-0.0.4.dist-info/LICENSE
cli_badges-0.0.4.dist-info/METADATA
cli_badges-0.0.4.dist-info/WHEEL
cli_badges-0.0.4.dist-info/top_level.txt
cli_badges-0.0.4.dist-info/RECORD
