Metadata-Version: 2.1
Name: cli-badges
Version: 0.0.4
Summary: Quirky little python package for generating badges for your cli apps
Home-page: https://github.com/haideralipunjabi/cli-badges
Author: Haider Ali Punjabi
Author-email: me@haideralipunjabi.com
License: UNKNOWN
Keywords: color,colour,paint,ansi,terminal,linux,python,cli,badges,cli-badges,terminal-badges,console,console-badges
Platform: UNKNOWN
Classifier: Programming Language :: Python :: 3
Classifier: Programming Language :: Python :: 3.0
Classifier: Programming Language :: Python :: 3.2
Classifier: Programming Language :: Python :: 3.3
Classifier: Programming Language :: Python :: 3.4
Classifier: Programming Language :: Python :: 3.5
Classifier: License :: OSI Approved :: MIT License
Classifier: Operating System :: OS Independent
Classifier: Development Status :: 5 - Production/Stable
Classifier: Environment :: Console
Classifier: Operating System :: POSIX
Classifier: Operating System :: POSIX :: Linux
Classifier: Operating System :: Microsoft
Classifier: Operating System :: Microsoft :: Windows
Classifier: Operating System :: Microsoft :: Windows :: Windows 10
Classifier: Operating System :: POSIX :: Other
Classifier: Programming Language :: Unix Shell
Classifier: Topic :: Terminals
Requires-Python: >=3.6
Requires-Dist: colored
